lmspace/__init__.py
lmspace/cli.py
lmspace/vscode/__init__.py
lmspace/vscode/agent_dispatch.py
lmspace/vscode/cli.py
lmspace/vscode/provision.py
lmspace/vscode/subagent_template/subagent.code-workspace
lmspace/vscode/subagent_template/wakeup.chatmode.md
lmspace-0.2.0.dist-info/WHEEL
lmspace-0.2.0.dist-info/entry_points.txt
lmspace-0.2.0.dist-info/METADATA
lmspace-0.2.0.dist-info/RECORD
