Metadata-Version: 2.3
Name: lmspace
Version: 0.2.0
Summary: Runner that provisions subagents from configs
License: MIT
Requires-Dist: openai>=2.4.0
Requires-Dist: pydantic>=2.12.2
Requires-Dist: pyyaml>=6.0.3
Requires-Dist: tenacity>=9.1.2
Requires-Dist: pytest>=8.4 ; extra == 'dev'
Requires-Dist: pytest-asyncio>=0.23 ; extra == 'dev'
Requires-Python: >=3.12
Provides-Extra: dev
